{
"title": {
"text": "Flow Map"
},
"subtitle": {
 "text": "Example"
},
"series": [{
"type": "map",
"name": "Flow",
"data": [
{
"from": {
"name": "Wien",
"lat": 48.2066,
"lon": 16.37341
},
"to":{
"name": "Szklarska Poręba",
"lat": 50.82567,
"lon": 15.52274
},
"weight": 100
},
{
"from": {
"name": "Szklarska Poręba",
"lat": 50.82567,
"lon": 15.52274
},
"to":{
"name": "Wien",
"lat": 48.2066,
"lon": 16.37341
},
"weight": 100
},
{
"from": {
"name": "Bad Ischl",
"lat": 47.71109,
"lon": 13.61893
},
"to":{
"name": "Insel Hiddensee",
"lat": 54.56689,
"lon": 13.10411
},
"weight": 100
},
{
"from": {
"name": "Wien",
"lat": 48.2066,
"lon": 16.37341
},
"to":{
"name": "Wien",
"lat": 48.2066,
"lon": 16.37341
},
"weight": 100
},
{
"from": {
"name": "Berlin",
"lat": 52.52437,
"lon": 13.41053
},
"to":{
"name": "Agnetendorf",
"lat": 50.816944,
"lon": 15.609444
},
"weight": 100
},
{
"from": {
"name": "Szklarska Poręba",
"lat": 50.82567,
"lon": 15.52274
},
"to":{
"name": "Wien",
"lat": 48.2066,
"lon": 16.37341
},
"weight": 100
},
{
"from": {
"name": "St. Gilgen",
"lat": 47.76667,
"lon": 13.36667
},
"to":{
"name": "Agnetendorf",
"lat": 50.816944,
"lon": 15.609444
},
"weight": 100
},
{
"from": {
"name": "Wien",
"lat": 48.2066,
"lon": 16.37341
},
"to":{
"name": "Berlin",
"lat": 52.52437,
"lon": 13.41053
},
"weight": 100
},
{
"from": {
"name": "Agnetendorf",
"lat": 50.816944,
"lon": 15.609444
},
"to":{
"name": "Wien",
"lat": 48.2066,
"lon": 16.37341
},
"weight": 100
},
{
"from": {
"name": "Agnetendorf",
"lat": 50.816944,
"lon": 15.609444
},
"to":{
"name": "Wien",
"lat": 48.2066,
"lon": 16.37341
},
"weight": 100
},
{
"from": {
"name": "Agnetendorf",
"lat": 50.816944,
"lon": 15.609444
},
"to":{
"name": "Wien",
"lat": 48.2066,
"lon": 16.37341
},
"weight": 100
},
{
"from": {
"name": "Agnetendorf",
"lat": 50.816944,
"lon": 15.609444
},
"to":{
"name": "Wien",
"lat": 48.2066,
"lon": 16.37341
},
"weight": 100
},
{
"from": {
"name": "Berlin",
"lat": 52.52437,
"lon": 13.41053
},
"to":{
"name": "Wien",
"lat": 48.2066,
"lon": 16.37341
},
"weight": 100
},
{
"from": {
"name": "Agnetendorf",
"lat": 50.816944,
"lon": 15.609444
},
"to":{
"name": "Wien",
"lat": 48.2066,
"lon": 16.37341
},
"weight": 100
},
{
"from": {
"name": "Wien",
"lat": 48.2066,
"lon": 16.37341
},
"to":{
"name": "Agnetendorf",
"lat": 50.816944,
"lon": 15.609444
},
"weight": 100
},
{
"from": {
"name": "Wien",
"lat": 48.2066,
"lon": 16.37341
},
"to":{
"name": "Agnetendorf",
"lat": 50.816944,
"lon": 15.609444
},
"weight": 100
}
]}
]
}